{
    "headers": {
        "Connection": "Keep-Alive",
        "Expect": "100-continue",
        "Host": "prod-24.westus2.logic.azure.com",
        "User-Agent": "IcMBroadcaster/1.0",
        "X-CorrelationContext": "RkkKACgAAAACAAAAEAAX42uR16BeTouFmyIJH0AVAQAQAAqyXSF0GGRAvCBrNQpNfLI=",
        "Content-Length": "1475",
        "Content-Type": "application/json; charset=utf-8"
    },
    "body": {
        "schemaId": "azureMonitorCommonAlertSchema",
        "data": {
            "essentials": {
                "alertId": "/subscriptions/b9c770d1-cde9-4da3-ae40-95ce1a4fac0c/providers/Microsoft.AlertsManagement/alerts/215db20a-1874-4064-bc20-6b350a4d7cb2",
                "alertRule": "cdw-ssasresourcehealth-20200411",
                "severity": "Sev4",
                "signalType": "Activity Log",
                "monitorCondition": "Fired",
                "monitoringService": "Resource Health",
                "alertTargetIDs": [
                    "/subscriptions/b9c770d1-cde9-4da3-ae40-95ce1a4fac0c/resourcegroups/cdw-analysisservices-20200401/providers/microsoft.analysisservices/servers/cdwanalysisservices20200401"
                ],
                "originAlertId": "2e2ebd54-9076-4b4b-b5cc-59b44e285e12",
                "firedDateTime": "2020-04-11T16:28:33.3138673Z",
                "description": null,
                "essentialsVersion": "1.0",
                "alertContextVersion": "1.0"
            },
            "alertContext": {
                "channels": "Admin, Operation",
                "correlationId": "49636a0e-663c-4aa8-9780-4cd333b6c15e",
                "eventSource": "ResourceHealth",
                "eventTimestamp": "2020-04-11T16:27:46.276+00:00",
                "eventDataId": "2e2ebd54-9076-4b4b-b5cc-59b44e285e12",
                "level": "Informational",
                "operationName": "Microsoft.Resourcehealth/healthevent/InProgress/action",
                "operationId": "2e2ebd54-9076-4b4b-b5cc-59b44e285e12",
                "properties": {
                    "title": "Server is paused. Resume the server to make it available. Server is paused. Resume the server to make it available.",
                    "details": "Detached",
                    "currentHealthStatus": "Unavailable",
                    "previousHealthStatus": "Unavailable",
                    "type": "Downtime",
                    "cause": "UserInitiated"
                },
                "status": "Updated",
                "submissionTimestamp": "2020-04-11T16:28:33.1349226+00:00"
            }
        }
    }
}